[
  {
    "Agency": "ADMIN FOR CHILDREN'S SVCS",
    "Average": "$66,812",
    "Male": "$65,666",
    "Female": "$67,320",
    "gap": "-1.2443%"
  },
  {
    "Agency": "ADMIN TRIALS AND HEARINGS",
    "Average": "$71,819",
    "Male": "$79,718",
    "Female": "$66,937",
    "gap": "8.7153%"
  },
  {
    "Agency": "BOARD OF ELECTION",
    "Average": "$54,865",
    "Male": "$56,514",
    "Female": "$52,987",
    "gap": "3.2212%"
  },
  {
    "Agency": "BRONX DISTRICT ATTORNEY",
    "Average": "$70,413",
    "Male": "$73,631",
    "Female": "$68,195",
    "gap": "3.8328%"
  },
  {
    "Agency": "CAMPAIGN FINANCE BOARD",
    "Average": "$86,166",
    "Male": "$85,729",
    "Female": "$86,720",
    "gap": "-0.5747%"
  },
  {
    "Agency": "CITY COUNCIL",
    "Average": "$97,596",
    "Male": "$100,224",
    "Female": "$94,406",
    "gap": "2.9891%"
  },
  {
    "Agency": "CIVILIAN COMPLAINT REVIEW BD",
    "Average": "$75,439",
    "Male": "$74,556",
    "Female": "$76,387",
    "gap": "-1.2129%"
  },
  {
    "Agency": "COMMUNITY COLLEGE (BRONX)",
    "Average": "$72,561",
    "Male": "$72,826",
    "Female": "$72,308",
    "gap": "0.3571%"
  },
  {
    "Agency": "COMMUNITY COLLEGE (HOSTOS)",
    "Average": "$71,254",
    "Male": "$72,355",
    "Female": "$70,417",
    "gap": "1.3575%"
  },
  {
    "Agency": "COMMUNITY COLLEGE (KINGSBORO)",
    "Average": "$75,520",
    "Male": "$76,117",
    "Female": "$75,089",
    "gap": "0.6798%"
  },
  {
    "Agency": "COMMUNITY COLLEGE (LAGUARDIA)",
    "Average": "$77,245",
    "Male": "$78,419",
    "Female": "$76,410",
    "gap": "1.2975%"
  },
  {
    "Agency": "COMMUNITY COLLEGE (MANHATTAN)",
    "Average": "$73,284",
    "Male": "$74,557",
    "Female": "$72,173",
    "gap": "1.6245%"
  },
  {
    "Agency": "COMMUNITY COLLEGE (QUEENSBORO)",
    "Average": "$76,617",
    "Male": "$77,213",
    "Female": "$76,130",
    "gap": "0.7063%"
  },
  {
    "Agency": "CONSUMER AFFAIRS",
    "Average": "$66,803",
    "Male": "$67,495",
    "Female": "$66,289",
    "gap": "0.9012%"
  },
  {
    "Agency": "DEPARTMENT FOR THE AGING",
    "Average": "$78,446",
    "Male": "$81,495",
    "Female": "$77,453",
    "gap": "2.5427%"
  },
  {
    "Agency": "DEPARTMENT OF BUILDINGS",
    "Average": "$75,428",
    "Male": "$79,189",
    "Female": "$68,364",
    "gap": "7.3366%"
  },
  {
    "Agency": "DEPARTMENT OF BUSINESS SERV.",
    "Average": "$80,862",
    "Male": "$80,515",
    "Female": "$81,143",
    "gap": "-0.3884%"
  },
  {
    "Agency": "DEPARTMENT OF CITY PLANNING",
    "Average": "$84,998",
    "Male": "$85,412",
    "Female": "$84,491",
    "gap": "0.5421%"
  },
  {
    "Agency": "DEPARTMENT OF CORRECTION",
    "Average": "$71,220",
    "Male": "$69,456",
    "Female": "$73,676",
    "gap": "-2.9483%"
  },
  {
    "Agency": "DEPARTMENT OF EDUCATION ADMIN",
    "Average": "$71,256",
    "Male": "$76,365",
    "Female": "$69,073",
    "gap": "5.0137%"
  },
  {
    "Agency": "DEPARTMENT OF FINANCE",
    "Average": "$75,563",
    "Male": "$81,347",
    "Female": "$70,085",
    "gap": "7.4367%"
  },
  {
    "Agency": "DEPARTMENT OF INVESTIGATION",
    "Average": "$83,046",
    "Male": "$86,163",
    "Female": "$79,994",
    "gap": "3.7130%"
  },
  {
    "Agency": "DEPARTMENT OF PROBATION",
    "Average": "$62,575",
    "Male": "$63,638",
    "Female": "$62,013",
    "gap": "1.2934%"
  },
  {
    "Agency": "DEPARTMENT OF SANITATION",
    "Average": "$73,487",
    "Male": "$74,439",
    "Female": "$64,766",
    "gap": "6.9484%"
  },
  {
    "Agency": "DEPARTMENT OF TRANSPORTATION",
    "Average": "$71,066",
    "Male": "$71,321",
    "Female": "$70,526",
    "gap": "0.5605%"
  },
  {
    "Agency": "DEPT OF CITYWIDE ADMIN SVCS",
    "Average": "$64,900",
    "Male": "$63,380",
    "Female": "$66,681",
    "gap": "-2.5379%"
  },
  {
    "Agency": "DEPT OF ED PARA PROFESSIONALS",
    "Average": "$37,513",
    "Male": "$36,648",
    "Female": "$37,715",
    "gap": "-1.4356%"
  },
  {
    "Agency": "DEPT OF ED PEDAGOGICAL",
    "Average": "$93,915",
    "Male": "$95,665",
    "Female": "$93,353",
    "gap": "1.2236%"
  },
  {
    "Agency": "DEPT OF ENVIRONMENT PROTECTION",
    "Average": "$77,460",
    "Male": "$79,126",
    "Female": "$73,896",
    "gap": "3.4183%"
  },
  {
    "Agency": "DEPT OF HEALTH/MENTAL HYGIENE",
    "Average": "$74,253",
    "Male": "$73,749",
    "Female": "$74,508",
    "gap": "-0.5120%"
  },
  {
    "Agency": "DEPT OF INFO TECH & TELECOMM",
    "Average": "$86,802",
    "Male": "$98,864",
    "Female": "$70,305",
    "gap": "16.8822%"
  },
  {
    "Agency": "DEPT OF PARKS & RECREATION",
    "Average": "$65,842",
    "Male": "$65,264",
    "Female": "$66,831",
    "gap": "-1.1860%"
  },
  {
    "Agency": "DEPT OF YOUTH & COMM DEV SRVS",
    "Average": "$83,986",
    "Male": "$86,307",
    "Female": "$82,533",
    "gap": "2.2348%"
  },
  {
    "Agency": "DEPT. OF DESIGN & CONSTRUCTION",
    "Average": "$85,704",
    "Male": "$88,680",
    "Female": "$80,797",
    "gap": "4.6517%"
  },
  {
    "Agency": "DEPT. OF HOMELESS SERVICES",
    "Average": "$55,229",
    "Male": "$52,912",
    "Female": "$57,568",
    "gap": "-4.2145%"
  },
  {
    "Agency": "DISTRICT ATTORNEY-MANHATTAN",
    "Average": "$77,954",
    "Male": "$79,534",
    "Female": "$76,771",
    "gap": "1.7678%"
  },
  {
    "Agency": "DISTRICT ATTORNEY-SPECIAL NARC",
    "Average": "$93,569",
    "Male": "$100,304",
    "Female": "$87,936",
    "gap": "6.5707%"
  },
  {
    "Agency": "DISTRICT ATTORNEY KINGS COUNTY",
    "Average": "$74,590",
    "Male": "$78,626",
    "Female": "$71,603",
    "gap": "4.6745%"
  },
  {
    "Agency": "DISTRICT ATTORNEY QNS COUNTY",
    "Average": "$80,851",
    "Male": "$86,833",
    "Female": "$76,745",
    "gap": "6.1676%"
  },
  {
    "Agency": "DISTRICT ATTORNEY RICHMOND COU",
    "Average": "$78,702",
    "Male": "$87,730",
    "Female": "$72,798",
    "gap": "9.3021%"
  },
  {
    "Agency": "FINANCIAL INFO SVCS AGENCY",
    "Average": "$111,227",
    "Male": "$113,002",
    "Female": "$107,601",
    "gap": "2.4484%"
  },
  {
    "Agency": "FIRE DEPARTMENT",
    "Average": "$76,193",
    "Male": "$78,152",
    "Female": "$60,091",
    "gap": "13.0649%"
  },
  {
    "Agency": "GUTTMAN COMMUNITY COLLEGE",
    "Average": "$86,456",
    "Male": "$87,107",
    "Female": "$85,989",
    "gap": "0.6461%"
  },
  {
    "Agency": "HOUSING PRESERVATION & DVLPMNT",
    "Average": "$71,907",
    "Male": "$74,073",
    "Female": "$69,718",
    "gap": "3.0290%"
  },
  {
    "Agency": "HRA/DEPT OF SOCIAL SERVICES",
    "Average": "$58,109",
    "Male": "$63,174",
    "Female": "$56,032",
    "gap": "5.9909%"
  },
  {
    "Agency": "HUMAN RIGHTS COMMISSION",
    "Average": "$74,733",
    "Male": "$73,683",
    "Female": "$75,769",
    "gap": "-1.3960%"
  },
  {
    "Agency": "HUNTER COLLEGE HIGH SCHOOL",
    "Average": "$75,398",
    "Male": "$79,284",
    "Female": "$73,406",
    "gap": "3.8499%"
  },
  {
    "Agency": "LAW DEPARTMENT",
    "Average": "$85,452",
    "Male": "$89,644",
    "Female": "$82,630",
    "gap": "4.0713%"
  },
  {
    "Agency": "MAYORS OFFICE OF CONTRACT SVCS",
    "Average": "$88,216",
    "Male": "$95,784",
    "Female": "$81,967",
    "gap": "7.7732%"
  },
  {
    "Agency": "NYC EMPLOYEES RETIREMENT SYS",
    "Average": "$74,293",
    "Male": "$82,101",
    "Female": "$68,569",
    "gap": "8.9809%"
  },
  {
    "Agency": "NYC HOUSING AUTHORITY",
    "Average": "$55,538",
    "Male": "$56,806",
    "Female": "$54,244",
    "gap": "2.3074%"
  },
  {
    "Agency": "NYC POLICE PENSION FUND",
    "Average": "$80,534",
    "Male": "$94,055",
    "Female": "$68,145",
    "gap": "15.9743%"
  },
  {
    "Agency": "OFF OF PAYROLL ADMINISTRATION",
    "Average": "$90,798",
    "Male": "$95,763",
    "Female": "$86,860",
    "gap": "4.8753%"
  },
  {
    "Agency": "OFFICE OF EMERGENCY MANAGEMENT",
    "Average": "$89,167",
    "Male": "$91,600",
    "Female": "$86,277",
    "gap": "2.9923%"
  },
  {
    "Agency": "OFFICE OF LABOR RELATIONS",
    "Average": "$84,841",
    "Male": "$95,978",
    "Female": "$79,170",
    "gap": "9.5962%"
  },
  {
    "Agency": "OFFICE OF MANAGEMENT & BUDGET",
    "Average": "$91,219",
    "Male": "$93,900",
    "Female": "$87,990",
    "gap": "3.2495%"
  },
  {
    "Agency": "OFFICE OF THE COMPTROLLER",
    "Average": "$88,932",
    "Male": "$94,426",
    "Female": "$84,192",
    "gap": "5.7293%"
  },
  {
    "Agency": "OFFICE OF THE MAYOR",
    "Average": "$105,532",
    "Male": "$107,799",
    "Female": "$104,163",
    "gap": "1.7155%"
  },
  {
    "Agency": "POLICE DEPARTMENT",
    "Average": "$75,579",
    "Male": "$81,813",
    "Female": "$62,074",
    "gap": "13.7182%"
  },
  {
    "Agency": "TAXI & LIMOUSINE COMMISSION",
    "Average": "$58,305",
    "Male": "$56,308",
    "Female": "$61,725",
    "gap": "-4.5898%"
  },
  {
    "Agency": "TEACHERS RETIREMENT SYSTEM",
    "Average": "$87,242",
    "Male": "$95,748",
    "Female": "$80,842",
    "gap": "8.4413%"
  }
]
